fasdr/__init__.py
fasdr/cli.py
fasdr/fasdr.py
fasdr-0.0.6.dist-info/METADATA
fasdr-0.0.6.dist-info/WHEEL
fasdr-0.0.6.dist-info/entry_points.txt
fasdr-0.0.6.dist-info/top_level.txt
fasdr-0.0.6.dist-info/RECORD
