Metadata-Version: 2.1
Name: fasdr
Version: 0.0.6
Summary: Simple dense retrieval using SciPy, spaCy, and Sentence-Transformers
Home-page: https://github.com/dmarx/fast-and-simple-dense-retrieval/
Author: David Marx
Author-email: david.marx84@gmail.com
Classifier: Development Status :: 3 - Alpha
Classifier: Intended Audience :: Developers
Classifier: License :: OSI Approved :: MIT License
Classifier: Programming Language :: Python :: 3.7
Classifier: Programming Language :: Python :: 3.8
Classifier: Programming Language :: Python :: 3.9
Classifier: Programming Language :: Python :: 3.10
Requires-Dist: numpy
Requires-Dist: spacy
Requires-Dist: sentence-transformers
Requires-Dist: scipy
Requires-Dist: spacy-sentence-bert
Requires-Dist: rich
